toothedsword/__init__.py
toothedsword/b64save.py
toothedsword/common.py
toothedsword/example_projects.py
toothedsword/exe_png2qgis.py
toothedsword/field.py
toothedsword/figures.py
toothedsword/png2qgis.py
toothedsword/projects.py
toothedsword/tiff2png.py
toothedsword/time_htht.py
toothedsword/base/flow.json
toothedsword/base/input.json
toothedsword/base/product.json
toothedsword/base/result.json
toothedsword/base/settings.json
toothedsword/base/step.json
toothedsword/ningxia/flow.json
toothedsword/ningxia/input.json
toothedsword/ningxia/product.json
toothedsword/ningxia/result.json
toothedsword/ningxia/settings.json
toothedsword/ningxia/step.json
toothedsword/tctb/flow.json
toothedsword/tctb/input.json
toothedsword/tctb/product.json
toothedsword/tctb/result.json
toothedsword/tctb/step.json
toothedsword-0.2.61.dist-info/METADATA
toothedsword-0.2.61.dist-info/WHEEL
toothedsword-0.2.61.dist-info/top_level.txt
toothedsword-0.2.61.dist-info/RECORD
