Metadata-Version: 2.4
Name: toothedsword
Version: 0.2.61
Summary: nothing
Requires-Python: >=3.6
Dynamic: requires-python
Dynamic: summary
